git_timesheet/__init__.py
git_timesheet/cli.py
git_timesheet/config.py
git_timesheet/formatters.py
git_timesheet/git_utils.py
git_timesheet/main.py
git_timesheet/timezone_utils.py
git_timesheet-0.1.3.dist-info/licenses/LICENSE
tests/__init__.py
tests/conftest.py
tests/test_formatting.py
tests/test_git_operations.py
tests/test_integration.py
tests/test_timezone.py
git_timesheet-0.1.3.dist-info/METADATA
git_timesheet-0.1.3.dist-info/WHEEL
git_timesheet-0.1.3.dist-info/entry_points.txt
git_timesheet-0.1.3.dist-info/top_level.txt
git_timesheet-0.1.3.dist-info/RECORD
