Metadata-Version: 2.4
Name: git-timesheet
Version: 0.1.3
Summary: Generate Git Timesheets from commit history
Home-page: https://github.com/mcgarrah/git_timesheet_python
Author: Michael McGarrah
Author-email: Michael McGarrah <mcgarrah@gmail.com>
License: MIT
Project-URL: Homepage, https://github.com/mcgarrah/git_timesheet_python
Project-URL: Bug Tracker, https://github.com/mcgarrah/git_timesheet_python/issues
Project-URL: Repository, https://github.com/mcgarrah/git_timesheet_python
Project-URL: Documentation, https://git-timesheet.readthedocs.io/en/latest/
Classifier: Development Status :: 4 - Beta
Classifier: Intended Audience :: Developers
Classifier: License :: OSI Approved :: MIT License
Classifier: Programming Language :: Python :: 3
Classifier: Programming Language :: Python :: 3.8
Classifier: Programming Language :: Python :: 3.9
Classifier: Programming Language :: Python :: 3.10
Classifier: Programming Language :: Python :: 3.11
Classifier: Programming Language :: Python :: 3.12
Requires-Python: >=3.8
License-File: LICENSE
Requires-Dist: pytz>=2021.1
Requires-Dist: click>=8.0.0
Provides-Extra: dev
Requires-Dist: pytest>=6.0; extra == "dev"
Requires-Dist: pytest-cov>=2.10; extra == "dev"
Requires-Dist: black>=22.3; extra == "dev"
Requires-Dist: flake8>=3.9; extra == "dev"
Requires-Dist: mypy>=0.910; extra == "dev"
Requires-Dist: isort>=5.0; extra == "dev"
Provides-Extra: docs
Requires-Dist: sphinx>=4.0; extra == "docs"
Requires-Dist: sphinx-rtd-theme>=1.0; extra == "docs"
Dynamic: author
Dynamic: home-page
Dynamic: license-file
Dynamic: requires-python
